demalign/__init__.py
demalign/cli.py
demalign/core.py
demalign-0.2.0.dist-info/licenses/LICENSE
demalign-0.2.0.dist-info/METADATA
demalign-0.2.0.dist-info/WHEEL
demalign-0.2.0.dist-info/entry_points.txt
demalign-0.2.0.dist-info/top_level.txt
demalign-0.2.0.dist-info/RECORD
