Metadata-Version: 2.4
Name: demalign
Version: 0.2.0
Summary: DEM alignment (Nuth & Kääb + optional ICP) via ASP pc_align/point2dem
Author: Aram Fathian, Dan Shugar
License: MIT
Keywords: DEM,alignment,coregistration,ASP,pc_align,point2dem,DoD
Classifier: Programming Language :: Python :: 3
Classifier: License :: OSI Approved :: MIT License
Classifier: Topic :: Scientific/Engineering :: GIS
Requires-Python: >=3.9
License-File: LICENSE
Requires-Dist: numpy>=1.23
Provides-Extra: dev
Requires-Dist: pytest>=7.4; extra == "dev"
Requires-Dist: ruff>=0.6; extra == "dev"
Requires-Dist: mypy>=1.10; extra == "dev"
Dynamic: license-file
